MANIFEST.in
README.rst
setup.py
pyspatiotemporalgeom/__init__.py
pyspatiotemporalgeom/componentMovingRegion.py
pyspatiotemporalgeom/intervalRegion.py
pyspatiotemporalgeom/region.py
pyspatiotemporalgeom/structureRegion.py
pyspatiotemporalgeom.egg-info/PKG-INFO
pyspatiotemporalgeom.egg-info/SOURCES.txt
pyspatiotemporalgeom.egg-info/dependency_links.txt
pyspatiotemporalgeom.egg-info/not-zip-safe
pyspatiotemporalgeom.egg-info/top_level.txt
pyspatiotemporalgeom/examples/__init__.py
pyspatiotemporalgeom/examples/gen.py
pyspatiotemporalgeom/examples/intervalRegTest.py
pyspatiotemporalgeom/examples/mapLibraryExamples.py
pyspatiotemporalgeom/examples/tempAggExample.py
pyspatiotemporalgeom/examples/temporalAggregate.py
pyspatiotemporalgeom/examples/test.py
pyspatiotemporalgeom/examples/triangleTest.py
pyspatiotemporalgeom/utilities/__init__.py
pyspatiotemporalgeom/utilities/convexHull.py
pyspatiotemporalgeom/utilities/hsegLibrary.py
pyspatiotemporalgeom/utilities/mapLibrary.py
pyspatiotemporalgeom/utilities/regionInterpolator.py
pyspatiotemporalgeom/utilities/regionOverlayGrid.py
pyspatiotemporalgeom/utilities/segLibrary.py
pyspatiotemporalgeom/utilities/temporalAggregate.py
pyspatiotemporalgeom/utilities/triangleLibrary.py
pyspatiotemporalgeom/utilities/zTestInter.py