Metadata-Version: 1.1
Name: pyspatiotemporalgeom
Version: 0.2.7.4
Summary: Spatiotemporal geometry libray. Curently a pure python library, not explicitly focused on speed.
Home-page: https://bitbucket.org/marmcke/pyspatiotemporalgeom
Author: Mark McKenney
Author-email: marmcke@siue.edu
License: MIT
Platform: UNKNOWN
Classifier: Development Status :: 3 - Alpha
Classifier: License :: OSI Approved :: MIT License
Classifier: Programming Language :: Python :: 2.7
Classifier: Topic :: Scientific/Engineering :: GIS
